win_shortcut/__init__.py
win_shortcut/_byref.py
win_shortcut/_icons.py
win_shortcut/_known_folder.py
win_shortcut/_known_folder_id.py
win_shortcut/_short_path.py
win_shortcut/_shortcut.py
win_shortcut/_winapi.py
win_shortcut/py.typed
win_shortcut-1.2.dist-info/METADATA
win_shortcut-1.2.dist-info/WHEEL
win_shortcut-1.2.dist-info/licenses/LICENSE
win_shortcut-1.2.dist-info/RECORD
