Metadata-Version: 2.4
Name: win-shortcut
Version: 1.2
Summary: TODO
Project-URL: Homepage, https://github.com/petamas/python-win-shortcut
Project-URL: Bug Tracker, https://github.com/petamas/python-win-shortcut/issues
Author-email: Tamás PEREGI <petamas@gmail.com>
License-Expression: MIT
License-File: LICENSE
Classifier: License :: OSI Approved :: MIT License
Classifier: Operating System :: Microsoft :: Windows
Classifier: Programming Language :: Python :: 3
Classifier: Programming Language :: Python :: 3.10
Classifier: Programming Language :: Python :: 3.11
Classifier: Programming Language :: Python :: 3.12
Classifier: Programming Language :: Python :: 3.13
Requires-Python: >=3.10
Requires-Dist: comtypes<2,>=1.4.11
Requires-Dist: mslex<2,>=1.3
Requires-Dist: ntstatus<3,>=2.0
